clarifai_grpc/__init__.py
clarifai_grpc/channel/__init__.py
clarifai_grpc/channel/clarifai_channel.py
clarifai_grpc/channel/errors.py
clarifai_grpc/channel/exceptions.py
clarifai_grpc/channel/grpc_json_channel.py
clarifai_grpc/channel/http_client.py
clarifai_grpc/channel/custom_converters/__init__.py
clarifai_grpc/channel/custom_converters/custom_dict_to_message.py
clarifai_grpc/channel/custom_converters/custom_message_to_dict.py
clarifai_grpc/grpc/__init__.py
clarifai_grpc/grpc/api/__init__.py
clarifai_grpc/grpc/api/resources_pb2.py
clarifai_grpc/grpc/api/resources_pb2.pyi
clarifai_grpc/grpc/api/resources_pb2_grpc.py
clarifai_grpc/grpc/api/service_pb2.py
clarifai_grpc/grpc/api/service_pb2.pyi
clarifai_grpc/grpc/api/service_pb2_grpc.py
clarifai_grpc/grpc/api/status/__init__.py
clarifai_grpc/grpc/api/status/status_code_pb2.py
clarifai_grpc/grpc/api/status/status_code_pb2.pyi
clarifai_grpc/grpc/api/status/status_code_pb2_grpc.py
clarifai_grpc/grpc/api/status/status_pb2.py
clarifai_grpc/grpc/api/status/status_pb2.pyi
clarifai_grpc/grpc/api/status/status_pb2_grpc.py
clarifai_grpc/grpc/api/utils/__init__.py
clarifai_grpc/grpc/api/utils/extensions_pb2.py
clarifai_grpc/grpc/api/utils/extensions_pb2.pyi
clarifai_grpc/grpc/api/utils/extensions_pb2_grpc.py
clarifai_grpc/grpc/api/utils/matrix_pb2.py
clarifai_grpc/grpc/api/utils/matrix_pb2.pyi
clarifai_grpc/grpc/api/utils/matrix_pb2_grpc.py
clarifai_grpc/grpc/api/utils/test_proto_pb2.py
clarifai_grpc/grpc/api/utils/test_proto_pb2.pyi
clarifai_grpc/grpc/api/utils/test_proto_pb2_grpc.py
clarifai_grpc/grpc/auth/__init__.py
clarifai_grpc/grpc/auth/scope/__init__.py
clarifai_grpc/grpc/auth/scope/scope_pb2.py
clarifai_grpc/grpc/auth/scope/scope_pb2.pyi
clarifai_grpc/grpc/auth/scope/scope_pb2_grpc.py
clarifai_grpc/grpc/auth/types/__init__.py
clarifai_grpc/grpc/auth/types/types_pb2.py
clarifai_grpc/grpc/auth/types/types_pb2.pyi
clarifai_grpc/grpc/auth/types/types_pb2_grpc.py
clarifai_grpc/grpc/auth/util/__init__.py
clarifai_grpc-12.0.12.dist-info/licenses/LICENSE
clarifai_grpc-12.0.12.dist-info/METADATA
clarifai_grpc-12.0.12.dist-info/WHEEL
clarifai_grpc-12.0.12.dist-info/top_level.txt
clarifai_grpc-12.0.12.dist-info/RECORD
