Metadata-Version: 2.4
Name: clarifai-grpc
Version: 12.0.12
Summary: Clarifai gRPC API Client
Home-page: https://github.com/Clarifai/clarifai-python-grpc
Author: Clarifai
Author-email: support@clarifai.com
License: Apache 2.0
Classifier: Topic :: Scientific/Engineering :: Artificial Intelligence
Classifier: Programming Language :: Python :: 3
Classifier: License :: OSI Approved :: Apache Software License
Classifier: Operating System :: OS Independent
Requires-Python: >=3.8
License-File: LICENSE
Requires-Dist: grpcio>=1.53.2; python_version < "3.13"
Requires-Dist: grpcio>=1.68.0; python_version >= "3.13"
Requires-Dist: protobuf>=5.29.5
Requires-Dist: googleapis-common-protos>=1.57.0
Dynamic: author
Dynamic: author-email
Dynamic: classifier
Dynamic: description
Dynamic: description-content-type
Dynamic: home-page
Dynamic: license
Dynamic: license-file
Dynamic: requires-dist
Dynamic: requires-python
Dynamic: summary
